api_cli.py
gaiaframework/__init__.py
gaiaframework/version.py
gaiaframework/base/__init__.py
gaiaframework/base/batch/__init__.py
gaiaframework/base/batch/dag_base.py
gaiaframework/base/batch/spark_base_stage.py
gaiaframework/base/batch/stage_base.py
gaiaframework/base/batch/workflow_base.py
gaiaframework/base/cloud_eval/__init__.py
gaiaframework/base/cloud_eval/cloud_eval_client_base.py
gaiaframework/base/cloud_eval/worker.py
gaiaframework/base/common/__init__.py
gaiaframework/base/common/async_iterator.py
gaiaframework/base/common/component.py
gaiaframework/base/common/functions.py
gaiaframework/base/common/object.py
gaiaframework/base/common/output_logger.py
gaiaframework/base/common/regex_handler.py
gaiaframework/base/common/streaming_generations.py
gaiaframework/base/pipeline/__init__.py
gaiaframework/base/pipeline/pipeline.py
gaiaframework/base/pipeline/artifacts/__init__.py
gaiaframework/base/pipeline/artifacts/shared_artifacts.py
gaiaframework/base/pipeline/forcers/__init__.py
gaiaframework/base/pipeline/postprocessor/__init__.py
gaiaframework/base/pipeline/postprocessor/postprocess.py
gaiaframework/base/pipeline/predictables/__init__.py
gaiaframework/base/pipeline/predictables/predictable.py
gaiaframework/base/pipeline/predictors/__init__.py
gaiaframework/base/pipeline/preprocessor/__init__.py
gaiaframework/base/pipeline/preprocessor/preprocess.py
gaiaframework/base/server/__init__.py
gaiaframework/base/server/server.py
gaiaframework/base/server/cache/__init__.py
gaiaframework/base/server/cache/cache.py
gaiaframework/base/server/cache/cache_utils.py
gaiaframework/base/server/cache/redis_cache.py
gaiaframework/base/server/tests/__init__.py
gaiaframework/base/server/tests/test_cache.py
gaiaframework/base/server/tests/test_cache_utils.py
gaiaframework/base/testable/__init__.py
gaiaframework/base/tester/__init__.py
gaiaframework/base/tester/evaluator_logic.py
gaiaframework/base/tester/tester_logic.py
gaiaframework/base/trainer/__init__.py
gaiaFramework-1.0.30.dist-info/METADATA
gaiaFramework-1.0.30.dist-info/WHEEL
gaiaFramework-1.0.30.dist-info/entry_points.txt
gaiaFramework-1.0.30.dist-info/top_level.txt
gaiaFramework-1.0.30.dist-info/RECORD
