Metadata-Version: 2.1
Name: gaiaFramework
Version: 1.0.30
Summary: Data science framework library
Author: oribrau@gmail.com
License: MIT License (MIT)
Requires-Dist: dvc[gs,s3] (==2.58.1)
Requires-Dist: click (==8.1.3)
Requires-Dist: pydantic (==1.10.7)
Requires-Dist: tldextract (==3.4.1)
Requires-Dist: uvicorn (==0.22.0)
Requires-Dist: gunicorn (==20.1.0)
Requires-Dist: fastapi (==0.95.1)
Requires-Dist: requests (==2.30.0)
Requires-Dist: Unidecode (==1.3.6)
Requires-Dist: python-json-logger (==2.0.7)
Requires-Dist: google-api-python-client (==2.86.0)
Requires-Dist: oauth2client (==4.1.3)
Requires-Dist: PyJWT (==2.7.0)
Requires-Dist: pandas (<1.4.0,>=1.2.4)
Requires-Dist: logdecorator (==2.4)
Requires-Dist: twine (==4.0.2)
Requires-Dist: wheel (==0.40.0)
Requires-Dist: awscliv2 (==2.2.0)
Requires-Dist: ujson (==5.7.0)
Requires-Dist: pymysql (==1.0.3)
Requires-Dist: redis (==4.5.5)
